{"stats":{"minecraft:dropped":{"strangeberries:invisibility_berries":2,"minecraft:sweet_berries":1,"strangeberries:fire_berries":1,"strangeberries:haste_berries":1},"minecraft:custom":{"minecraft:jump":9,"minecraft:time_since_rest":1527,"minecraft:crouch_one_cm":195,"minecraft:leave_game":1,"minecraft:sprint_one_cm":1066,"minecraft:play_time":1527,"minecraft:time_since_death":1527,"minecraft:walk_one_cm":5665,"minecraft:sneak_time":32,"minecraft:total_world_time":1557,"minecraft:drop":5,"minecraft:fly_one_cm":2356},"minecraft:used":{"strangeberries:invisibility_berries":2},"minecraft:picked_up":{"strangeberries:fire_berries":1,"strangeberries:invisibility_berries":2,"strangeberries:resistance_berries":2,"minecraft:sweet_berries":1,"strangeberries:haste_berries":1}},"DataVersion":3120}